src/__init__.py
src/add_data_noise.py
src/aerodexx.py
src/generate_aero_data_su2.py
src/gpr.py
src/modify_data.py
gpaero-0.0.1.dist-info/METADATA
gpaero-0.0.1.dist-info/WHEEL
gpaero-0.0.1.dist-info/licenses/LICENSE
gpaero-0.0.1.dist-info/RECORD
